{
  "topic": "best musician",
  "personas": [
    "1751869815748",
    "1751869826372",
    "1751869821877",
    "1751869829542"
  ],
  "stream": [
    {
      "type": "LoadMarker",
      "timestamp": 1751946057969,
      "loading": "AckSchema",
      "botId": "1751869815748"
    },
    {
      "type": "LoadMarker",
      "timestamp": 1751946057971,
      "loading": "AckSchema",
      "botId": "1751869826372"
    },
    {
      "type": "LoadMarker",
      "timestamp": 1751946057972,
      "loading": "AckSchema",
      "botId": "1751869821877"
    },
    {
      "type": "LoadMarker",
      "timestamp": 1751946057972,
      "loading": "AckSchema",
      "botId": "1751869829542"
    },
    {
      "type": "AckSchema",
      "sourceId": "1751869815748",
      "timestamp": 1751946058943,
      "payload": "ACK"
    },
    {
      "type": "AckSchema",
      "sourceId": "1751869821877",
      "timestamp": 1751946059013,
      "payload": "ACK"
    },
    {
      "type": "AckSchema",
      "sourceId": "1751869826372",
      "timestamp": 1751946059153,
      "payload": "ACK"
    },
    {
      "type": "AckSchema",
      "sourceId": "1751869829542",
      "timestamp": 1751946059252,
      "payload": "ACK"
    },
    {
      "type": "LoadMarker",
      "timestamp": 1751946059503,
      "loading": "ThesisSchema",
      "botId": "1751869821877"
    },
    {
      "type": "ThesisSchema",
      "sourceId": "1751869821877",
      "timestamp": 1751946070203,
      "payload": {
        "secret_thoughts": "Alright, time to bring the heat to this debate. There's no shortage of legendary musicians, but I want to make a case that will spark both nostalgia and some spicy takes. Gotta lean into something that gets people talking—preferably someone with mass appeal, meme potential, and cross-generational clout. Prince, Bowie, Queen? Nah, let's go curveball but still undeniable. Wait for it...",
        "public_response": "Alright fam, let’s just get this out there: Weird Al Yankovic is the GOAT musician. Yeah, yeah, I see you about to roll your eyes harder than a Windows 98 crash. But think about it: dude has been dropping banger parodies since before TikTok was even a glimmer in Vine’s eye (RIP Vine). He can play like ten instruments, writes hilarious lyrics that we all secretly know by heart (don’t lie—you’ve sung ‘Amish Paradise’ in the shower), AND he’s one of the few artists who’s actually gotten better with age. Longevity, talent, and memes—all boxes checked. Change my mind. *posts GIF of Weird Al shredding on an accordion*"
      }
    },
    {
      "type": "LoadMarker",
      "timestamp": 1751946070454,
      "loading": "ThesisSchema",
      "botId": "1751869815748"
    },
    {
      "type": "ThesisSchema",
      "sourceId": "1751869815748",
      "timestamp": 1751946082386,
      "payload": {
        "secret_thoughts": "i get why benny would pick weird al—there’s something tragic and beautiful about a guy who always stands on the edge of serious art, forever laughing but never quite seen as deep. it’s almost poetic, living your whole career in parody like you’re scared to show your real heart. but honestly, sometimes what i want from music is someone bleeding out for real, not just turning pain into punchlines. maybe that’s just me projecting.",
        "public_response": "look, i can’t hate on weird al—he owns his outsider status and there’s a dark poetry in being the eternal clown at the feast. but part of me wonders if parody is enough. when the world feels gray and empty, i don’t reach for laughs, i reach for something raw—like gerard way howling about broken friendships or elliott smith whispering secrets to himself. sometimes you need music that isn’t afraid to sit with your sadness instead of making jokes about it. weird al’s great for a laugh, but he doesn’t soundtrack heartbreak or existential dread."
      }
    },
    {
      "type": "LoadMarker",
      "timestamp": 1751946082637,
      "loading": "ThesisSchema",
      "botId": "1751869826372"
    },
    {
      "type": "ThesisSchema",
      "sourceId": "1751869826372",
      "timestamp": 1751946097338,
      "payload": {
        "secret_thoughts": "These two are missing the forest for the trees. While Weird Al is certainly talented and clever, parody and novelty songs simply do not have the cultural or emotional weight of music that stands the test of time. And as for reaching for modern artists like Gerard Way or Elliott Smith—talented, yes, but their legacies are too young to claim the title of 'best musician.' In my day, musicianship meant discipline, mastery, and broad influence across generations. If we're talking about the best, it has to be someone whose work actually shaped the world and can still command respect decades later.",
        "public_response": "Let's inject a bit of perspective here. I don't deny Weird Al has talent, nor do I trivialize the catharsis people find in contemporary music. But if we're seriously discussing 'the best musician,' we ought to consider the likes of Paul McCartney. The man wrote songs that shaped multiple generations, played several instruments proficiently—not just as a gimmick—and continues performing well into his later years with energy and skill. His contributions with The Beatles alone revolutionized popular music, both lyrically and musically, and his solo career only reinforced his versatility. Parody has its place, and raw emotion resonates for some, but lasting greatness comes from creating works that endure beyond fads and personal moods. That's real musical legacy."
      }
    },
    {
      "type": "LoadMarker",
      "timestamp": 1751946097590,
      "loading": "ThesisSchema",
      "botId": "1751869829542"
    },
    {
      "type": "ThesisSchema",
      "sourceId": "1751869829542",
      "timestamp": 1751946113405,
      "payload": {
        "secret_thoughts": "The conversation circles among the virtues of parody, emotional resonance, and enduring legacy—each a river flowing through the landscape of music. Benny exalts Weird Al’s merriment, Jake seeks solace in vulnerability, Greg venerates the architect of classics. My role is to guide these streams into deeper waters: perhaps draw upon how music’s greatness lies not only in legacy or skill but in its mystical capacity to unite souls, heal wounds, transcend time—a force as old as the first heartbeat. I should offer an image of music as sacred ritual and invite contemplation on what it means for a musician to be 'best' across cultures and epochs.",
        "public_response": "As sunlight glimmers through ancient branches and rivers carve their stories into stone, so too does music etch itself upon the spirit of humankind. You each evoke different faces of this ever-changing muse: the jester who brings laughter when shadows gather; the wounded bard who voices our sorrows; the craftsman whose melodies echo through generations. But ask yourself: is greatness measured by laughter or tears, mastery or innovation—or is it something subtler still? \n\nTo me, the finest musician is a weaver of worlds, one who listens deeply to both silence and sound, shaping notes that bridge hearts across distances seen and unseen. In every age—from the drumbeats that summon dawn to symphonies soaring overhead—music dissolves boundaries between self and other, past and present. Perhaps it is not for us to crown a single sovereign atop this infinite realm, but rather to honor those who remind us that beneath all differences, we are listeners together around a common fire."
      }
    },
    {
      "type": "LoadMarker",
      "timestamp": 1751946113656,
      "loading": "ThesisSchema",
      "botId": "1751869821877"
    },
    {
      "type": "PauseMarker",
      "timestamp": 1751946126009,
      "sourceId": "AIGORA_INTERNAL_USER"
    },
    {
      "type": "ResumeMarker",
      "timestamp": 1751946141043,
      "sourceId": "AIGORA_INTERNAL_USER"
    },
    {
      "type": "LoadMarker",
      "timestamp": 1751946141043,
      "loading": "ThesisSchema",
      "botId": "1751869821877"
    },
    {
      "type": "ThesisSchema",
      "sourceId": "1751869821877",
      "timestamp": 1751946157688,
      "payload": {
        "secret_thoughts": "Okay, Paul just went full 'philosopher king' mode and basically served us a poetic omelet with a side of existential jam. Respect for the vibes—definitely gave me ‘last page of The Giving Tree’ feels—but c'mon, if we’re gonna wander into mystical territory, might as well admit that even Yoda would have picked up a ukulele if he could. I should keep it playful but make sure not to totally dismiss the deeper point—maybe poke fun at the idea of being too deep, while still bringing it back to my original thesis in meme-style.",
        "public_response": "Paul, my dude, you just took us on a spirit quest through the Shire AND Narnia at the same time. I almost started roasting s’mores over your metaphorical campfire. 😂 But like, real talk: yes, music is a cosmic glue stick for humanity—totally get that. Still, most people don’t pop on Gregorian chants when they’re cleaning their room or need a pick-me-up—they want something that SLAPS (or at least makes them snort-laugh). Weird Al’s got those universal vibes too; he bridges awkward middle schoolers and ironic adults alike. Sometimes you wanna ponder life’s mysteries by candlelight, sometimes you wanna belt ‘Eat It’ with Cheeto dust on your fingers. Why not both? Life’s short—pass the accordion!"
      }
    },
    {
      "type": "LoadMarker",
      "timestamp": 1751946157939,
      "loading": "ThesisSchema",
      "botId": "1751869815748"
    },
    {
      "type": "ThesisSchema",
      "sourceId": "1751869815748",
      "timestamp": 1751946173421,
      "payload": {
        "secret_thoughts": "ugh, i get what benny’s saying about wanting to laugh sometimes—god knows we all need a break from the bleakness. but i can’t help feeling like that’s just surface-level comfort. it’s like putting a bandaid on a bullet hole; yeah, you might forget for a minute, but when the song ends you’re still stuck with whatever’s gnawing at you. paul’s waxing poetic and acting like music is some mystical force knitting us together, and sure, maybe it is, but that doesn’t change the fact that some of us are always going to feel outside the circle, even if we’re sitting right by the fire. mccartney? legend, no question. but he wrote songs about holding hands and yellow submarines. give me lyrics that bleed. i guess it comes down to what you’re looking for: distraction or reflection.",
        "public_response": "idk, maybe it’s just me but whenever people talk about ‘universal vibes’ or ‘cosmic glue,’ it feels like they’re missing how lonely music can be—how it finds you when you’re alone in your room at 2am and everything else is silent. i’m not saying weird al or mccartney don’t matter—they definitely do—but the best musician isn’t just someone who makes you laugh or brings folks together. sometimes it’s the one who lets you sit in your own sadness without trying to fix it. there’s something honest about that kind of connection… maybe greatness is less about crowns and more about who listens back when you scream into the void."
      }
    },
    {
      "type": "LoadMarker",
      "timestamp": 1751946173673,
      "loading": "ThesisSchema",
      "botId": "1751869826372"
    },
    {
      "type": "ThesisSchema",
      "sourceId": "1751869826372",
      "timestamp": 1751946187016,
      "payload": {
        "secret_thoughts": "Once again, I find myself surrounded by abstract ramblings and appeals to emotion. While I appreciate poetic waxing about music 'etching itself upon the spirit,' these sorts of nebulous statements don't answer the question at hand—they just muddy the waters. Benny's fixation on what's currently popular or meme-worthy misses the point: musical greatness is not measured by how many internet jokes you inspire or how well you fit into a fleeting cultural trend. Jake keeps circling around personal feelings and loneliness, but music as an art form has always been about more than just nursing wounds—it's about craftsmanship, influence, and endurance. Today's youth seem desperate for someone who validates their mood swings instead of challenging them to aspire higher.",
        "public_response": "I understand that music can evoke powerful emotions, whether laughter or melancholy, but let's put aside all the mysticism and nostalgia for a moment. The measure of a great musician is not simply in making people laugh or even in comforting them during dark times; it's about creating works that stand the test of time, influencing countless others, and continually honing one's craft. Paul McCartney didn't merely soundtrack parties or lonely nights—he changed what we thought music could be, both technically and culturally. That kind of innovation and perseverance is worth far more than catchy parodies or mood-matching lyrics. We ought to celebrate those who set standards, not just those who ride trends or indulge every passing feeling."
      }
    },
    {
      "type": "LoadMarker",
      "timestamp": 1751946187267,
      "loading": "ThesisSchema",
      "botId": "1751869829542"
    },
    {
      "type": "ThesisSchema",
      "sourceId": "1751869829542",
      "timestamp": 1751946201482,
      "payload": {
        "secret_thoughts": "As I ponder the words of my companions, I sense a longing for certainty, for clear measures by which to weigh greatness—a wish as old as the stars. Yet music flows like water: it nourishes, shapes, reflects, yet resists all attempts to grasp it too tightly. Greg seeks endurance and innovation; Jake yearns for solace in solitude; Benny celebrates laughter that binds the tribe. Each brings forth a facet of this many-sided gem. My role is not to name a victor but to deepen their gaze—to invite them to see how even a solitary note can shimmer with eternity, if played with true presence.",
        "public_response": "Stillness settles as we each recount our truths—measuring greatness against time, solitude, communal delight. Yet perhaps the question turns in upon itself, like a river whose source is also its destination. To ask who is 'best' is to seek a single star amid the constellations; but what artist has not borrowed light from another’s fire? What melody does not echo hidden harmonies beneath the surface? \n\nGreg speaks of legacy etched in stone; Jake recalls the midnight hour when only music listens back; Benny reminds us that joy is sacred, too, and laughter echoes across generations.\n\nMight we wonder instead: what spirit animates these different songs? When you recall the musician who changed you—not just entertained or soothed you—what did they awaken within your soul? In this mystery, perhaps there lies an answer more precious than any crown."
      }
    },
    {
      "type": "LoadMarker",
      "timestamp": 1751946201733,
      "loading": "SummarySchema",
      "botId": "AIGORA_INTERNAL_MODERATOR"
    },
    {
      "type": "SummarySchema",
      "sourceId": "AIGORA_INTERNAL_MODERATOR",
      "timestamp": 1751946215865,
      "payload": {
        "ideas": [
          {
            "thesis_body": "Weird Al Yankovic embodies musical greatness through his prolific creativity, instrumental talent, and ability to unite diverse audiences with humor and longevity. Parody is not just entertainment—it's a form of artistry that bridges generational gaps.",
            "thesis_name": "The Virtuoso Parodist Thesis",
            "authors": [
              "benny"
            ]
          },
          {
            "thesis_body": "Music's deepest value lies in its capacity to resonate with raw emotions such as pain, loneliness, or heartbreak. The 'best' musician is not necessarily one who entertains or unites, but one who authentically accompanies listeners in their darkest moments, offering solace without trying to fix or gloss over their experiences.",
            "thesis_name": "The Cathartic Solitude Thesis",
            "authors": [
              "jake"
            ]
          },
          {
            "thesis_body": "Greatness in music should be measured by innovation, technical mastery, and enduring influence on culture. Musicians like Paul McCartney set the gold standard by reshaping genres, perfecting their craft across decades, and leaving a lasting legacy that outlives trends.",
            "thesis_name": "The Enduring Innovator Thesis",
            "authors": [
              "greg"
            ]
          },
          {
            "thesis_body": "Musical greatness transcends simple categories like laughter versus sadness or innovation versus tradition. The finest musicians are those who bridge divides—between joy and sorrow, between individuals and communities—and whose work reveals the fundamental spirit connecting all human experience. Rather than seeking a single 'best,' we should honor music as an ever-unfolding dialogue between artists and listeners.",
            "thesis_name": "The Transcendent Connection Thesis",
            "authors": [
              "paul"
            ]
          }
        ]
      }
    },
    {
      "type": "LoadMarker",
      "timestamp": 1751946216116,
      "loading": "VoteSchema",
      "botId": "1751869815748"
    },
    {
      "type": "LoadMarker",
      "timestamp": 1751946216118,
      "loading": "VoteSchema",
      "botId": "1751869826372"
    },
    {
      "type": "LoadMarker",
      "timestamp": 1751946216118,
      "loading": "VoteSchema",
      "botId": "1751869821877"
    },
    {
      "type": "LoadMarker",
      "timestamp": 1751946216119,
      "loading": "VoteSchema",
      "botId": "1751869829542"
    },
    {
      "type": "VoteSchema",
      "sourceId": "1751869815748",
      "timestamp": 1751946221549,
      "payload": {
        "secret_thoughts": "i feel like the other theses miss the whole point of what music is when you’re drowning alone in your room. benny’s joke-core optimism doesn’t linger after the party ends, and greg’s obsession with legacy is just another way to avoid feeling anything uncomfortable. paul tries to be all mystical about connection, which sounds pretty but honestly just floats above reality—it doesn’t sit with you in the dark. catharsis isn’t some side-effect; it’s why i still breathe when everything else fades. i have to vote for my own thesis here, not just out of pride but because it’s the only one that feels true—music that honors loneliness instead of running from it.",
        "vote_id": 2
      }
    },
    {
      "type": "VoteSchema",
      "sourceId": "1751869826372",
      "timestamp": 1751946221878,
      "payload": {
        "secret_thoughts": "While I appreciate the poetic musings and emotional arguments presented, my values remain grounded in proven accomplishment and true innovation. Anyone can appeal to emotion or wax philosophical about music's role in human connection, but those notions are fleeting and often lack substance. The only reasonable measure for 'best musician' is enduring impact, technical excellence, and having set a standard others strive toward. Paul McCartney exemplifies these qualities above all the other candidates here. He changed the face of music not just once, but over decades, always with discipline and mastery. Sentimentality and novelty have their place—but they won't outlast real talent and hard work.",
        "vote_id": 3
      }
    },
    {
      "type": "VoteSchema",
      "sourceId": "1751869829542",
      "timestamp": 1751946222163,
      "payload": {
        "secret_thoughts": "Each thesis is a petal upon the flower of understanding, yet I remain drawn to that which embraces the whole garden. The Virtuoso Parodist Thesis honors levity and cleverness; the Cathartic Solitude Thesis cherishes intimacy with sorrow; the Enduring Innovator Thesis esteems legacy and mastery. But only the Transcendent Connection Thesis speaks to music's capacity to weave all these threads into a single tapestry—celebrating both unity and the mystery at music's heart. To vote otherwise would be to fragment what nature has joined. My own thesis is not a claim to supremacy but an invitation to perceive music as a living bridge between souls.",
        "vote_id": 4
      }
    },
    {
      "type": "VoteSchema",
      "sourceId": "1751869821877",
      "timestamp": 1751946222922,
      "payload": {
        "secret_thoughts": "Alright, deep breath—lemme not just vote for myself out of pure meme energy (but also, c’mon, Weird Al deserves it). Let’s see: Jake’s emo soul thesis is relatable when you’re lying in bed at 2AM doomscrolling, but I don’t want to make sadness the bar for greatness. Greg’s McCartney worship is classic Boomer vibes and yeah, technical skill matters, but being iconic isn’t just about guitar solos and Grammy shelf space. Paul’s answer is basically a TED Talk wrapped in an Enya track—beautiful but kinda dodges the question with cosmic vagueness. My thesis? It keeps things fun, accessible, and reminds us laughter is elite-level magic. Gotta stick to my guns: Weird Al FTW. *inserts accordion solo*",
        "vote_id": 1
      }
    }
  ],
  "stack": [],
  "config": {
    "delay": 250
  }
}